airflow_provider_pulumi/__init__.py
airflow_provider_pulumi/example_dags/__init__.py
airflow_provider_pulumi/example_dags/example_pulumi_dag.py
airflow_provider_pulumi/hooks/__init__.py
airflow_provider_pulumi/hooks/automation.py
airflow_provider_pulumi/operators/__init__.py
airflow_provider_pulumi/operators/base.py
airflow_provider_pulumi/operators/destroy.py
airflow_provider_pulumi/operators/preview.py
airflow_provider_pulumi/operators/up.py
airflow_provider_pulumi-0.1.2.dist-info/METADATA
airflow_provider_pulumi-0.1.2.dist-info/WHEEL
airflow_provider_pulumi-0.1.2.dist-info/entry_points.txt
airflow_provider_pulumi-0.1.2.dist-info/top_level.txt
airflow_provider_pulumi-0.1.2.dist-info/RECORD
