Metadata-Version: 2.1
Name: airflow-provider-pulumi
Version: 0.1.2
Summary: Apache Airflow Pulumi provider containing Operators & Hooks.
Home-page: https://github.com/astronomer/airflow-provider-pulumi
Author: Dylan Intorf
Author-email: dylan.intorf@astronomer.io
License: Apache License 2.0
Project-URL: Source Code, https://github.com/astronomer/airflow-provider-pulumi
Project-URL: Homepage, https://github.com/astronomer/airflow-provider-pulumi
Project-URL: Changelog, https://github.com/astronomer/airflow-provider-pulumi/blob/main/CHANGELOG.md
Classifier: Environment :: Web Environment
Classifier: Intended Audience :: Developers
Classifier: License :: OSI Approved :: Apache Software License
Classifier: Operating System :: OS Independent
Classifier: Programming Language :: Python
Classifier: Programming Language :: Python :: 3
Classifier: Programming Language :: Python :: 3.7
Classifier: Programming Language :: Python :: 3.8
Classifier: Programming Language :: Python :: 3.9
Requires-Python: >=3.7
Requires-Dist: apache-airflow (>=2.2.0)
Requires-Dist: pulumi (<4.0.0,>=3.0.0)
Provides-Extra: dev
Requires-Dist: mypy (>=0.800) ; extra == 'dev'
Requires-Dist: pytest ; extra == 'dev'
Requires-Dist: pre-commit ; extra == 'dev'
